EasyDSA/__init__.py
EasyDSA/binarySearchTree.py
EasyDSA/hashMap.py
EasyDSA/linkedList.py
tests/__init__.py
tests/datastructure_example.py
tests/test_binary_search_tree.py
tests/test_hash_map.py
tests/test_linked_list.py
EasyDSA-0.0.2.dist-info/LICENSE
EasyDSA-0.0.2.dist-info/METADATA
EasyDSA-0.0.2.dist-info/WHEEL
EasyDSA-0.0.2.dist-info/top_level.txt
EasyDSA-0.0.2.dist-info/RECORD
