Metadata-Version: 2.1
Name: EasyDSA
Version: 0.0.2
Summary: A Data Structures and Algorithms collection written in Pyhton which helps developers in implementing fast and efficient algorithms
Home-page: https://github.com/mad-skull/EasyDSA.git
Author: Deep Awasthi
Author-email: da.madskull@gmail.com
License: UNKNOWN
Platform: UNKNOWN
Classifier: Programming Language :: Python :: 3
Classifier: License :: OSI Approved :: MIT License
Classifier: Operating System :: OS Independent
Requires-Python: >=3.5
